[
    { "game_title": "red", "release_date": "1998-09-28T00:00:00.000Z" },
    { "game_title": "blue", "release_date": "1999-09-28T00:00:00.000Z" },
    { "game_title": "yellow", "release_date": "1998-09-12T00:00:00.000Z" },
    { "game_title": "gold", "release_date": "1999-11-21T00:00:00.000Z" },
    { "game_title": "silver", "release_date": "1999-11-21T00:00:00.000Z" },
    { "game_title": "crystal", "release_date": "2000-12-14T00:00:00.000Z" },
    { "game_title": "ruby", "release_date": "2002-11-21T00:00:00.000Z" },
    { "game_title": "sapphire", "release_date": "2002-11-21T00:00:00.000Z" },
    { "game_title": "emerald", "release_date": "2004-09-16T00:00:00.000Z" },
    { "game_title": "firered", "release_date": "2004-01-29T00:00:00.000Z" },
    { "game_title": "leafgreen", "release_date": "2004-01-29T00:00:00.000Z" },
    { "game_title": "diamond", "release_date": "2006-01-28T00:00:00.000Z" },
    { "game_title": "pearl", "release_date": "2006-09-28T00:00:00.000Z" },
    { "game_title": "platinum", "release_date": "2008-01-13T00:00:00.000Z" },
    { "game_title": "heartgold", "release_date": "2009-09-11T23:00:00.000Z" },
    { "game_title": "soulsilver", "release_date": "2009-09-11T23:00:00.000Z" },
    { "game_title": "black", "release_date": "2010-09-17T23:00:00.000Z" },
    { "game_title": "white", "release_date": "2010-09-17T23:00:00.000Z" },
    { "game_title": "black-2", "release_date": "2012-06-22T23:00:00.000Z" },
    { "game_title": "white-2", "release_date": "2012-06-22T23:00:00.000Z" },
    { "game_title": "x", "release_date": "2013-10-11T23:00:00.000Z" },
    { "game_title": "y", "release_date": "2013-10-11T23:00:00.000Z" },
    { "game_title": "omega-ruby", "release_date": "2014-11-21T00:00:00.000Z" },
    { "game_title": "alpha-sapphire", "release_date": "2014-11-21T00:00:00.000Z" },
    { "game_title": "sun", "release_date": "2016-11-18T00:00:00.000Z" },
    { "game_title": "moon", "release_date": "2016-11-18T00:00:00.000Z" },
    { "game_title": "ultra-sun", "release_date": "2017-11-17T00:00:00.000Z" },
    { "game_title": "ultra-moon", "release_date": "2017-11-17T00:00:00.000Z" },
    { "game_title": "lets-go-pikachu", "release_date": "2018-11-16T00:00:00.000Z" },
    { "game_title": "lets-go-eevee", "release_date": "2018-11-16T00:00:00.000Z" },
    { "game_title": "sword", "release_date": "2019-11-15T00:00:00.000Z" },
    { "game_title": "shield", "release_date": "2019-11-15T00:00:00.000Z" },
    { "game_title": "brilliant-diamond", "release_date": "2021-11-19T00:00:00.000Z" },
    { "game_title": "shining-pearl", "release_date": "2021-11-19T00:00:00.000Z" },
    { "game_title": "legends-arceus", "release_date": "2022-01-28T00:00:00.000Z" },
    { "game_title": "scarlet", "release_date": "2022-11-18T00:00:00.000Z" },
    { "game_title": "violet", "release_date": "2022-11-18T00:00:00.000Z" }
]